Workbook

Sheet Raw Data
A1: Order ID | B1: Customer Name | C1: Product | D1: Category | E1: Numbers | F1: Currency | G1: Currency2 | H1: percentage % | I1: City | J1: Date | K1: Payment Method | L1: Gross Sales | M1: Discount amount | N1: Net Sales | O1: Total Cost | P1: Profit
A2: ORD101 | B2: Ali Khan | C2: Laptop | D2: Electronics | E2: 1 | F2: 120000 | G2: 100000 | H2: 0.05 | I2: Islamabad | J2: 46031 | K2: Card | L2: =E2*F2 -> 120000 | M2: =L2*H2 -> 6000 | N2: =L2-M2 -> 114000 | O2: =E2*G2 -> 100000 | P2: =N2-O2 -> 14000
A3: ORD102 | B3: Ahmed Raza | C3: Mouse | D3: Accessories | E3: 3 | F3: 2500 | G3: 1800 | H3: 0.1 | I3: Rawalpindi | J3: 46062 | K3: Cash | L3: =E3*F3 -> 7500 | M3: =L3*H3 -> 750 | N3: =L3-M3 -> 6750 | O3: =E3*G3 -> 5400 | P3: =N3-O3 -> 1350
A4: ORD103 | B4: Sara Malik | C4: Keyboard | D4: Accessories | E4: 2 | F4: 4500 | G4: 3000 | H4: 0.05 | I4: Lahore | J4: 46090 | K4: JazzCash | L4: =E4*F4 -> 9000 | M4: =L4*H4 -> 450 | N4: =L4-M4 -> 8550 | O4: =E4*G4 -> 6000 | P4: =N4-O4 -> 2550
A5: ORD104 | B5: Hamza Ali | C5: Monitor | D5: Electronics | E5: 2 | F5: 45000 | G5: 36000 | H5: 0.08 | I5: Islamabad | J5: 46121 | K5: Card | L5: =E5*F5 -> 90000 | M5: =L5*H5 -> 7200 | N5: =L5-M5 -> 82800 | O5: =E5*G5 -> 72000 | P5: =N5-O5 -> 10800
A6: ORD105 | B6: Ayesha Noor | C6: Headphones | D6: Electronics | E6: 3 | F6: 8500 | G6: 6000 | H6: 0.1 | I6: Karachi | J6: 46151 | K6: Easypaisa | L6: =E6*F6 -> 25500 | M6: =L6*H6 -> 2550 | N6: =L6-M6 -> 22950 | O6: =E6*G6 -> 18000 | P6: =N6-O6 -> 4950
A7: ORD106 | B7: Usman Tariq | C7: USB Cable | D7: Accessories | E7: 5 | F7: 1200 | G7: 700 | H7: 0 | I7: Lahore | J7: 46182 | K7: Cash | L7: =E7*F7 -> 6000 | M7: =L7*H7 -> 0 | N7: =L7-M7 -> 6000 | O7: =E7*G7 -> 3500 | P7: =N7-O7 -> 2500
A8: ORD107 | B8: Hira Ahmed | C8: Laptop Stand | D8: Accessories | E8: 2 | F8: 6000 | G8: 4200 | H8: 0.05 | I8: Rawalpindi | J8: 46212 | K8: Card | L8: =E8*F8 -> 12000 | M8: =L8*H8 -> 600 | N8: =L8-M8 -> 11400 | O8: =E8*G8 -> 8400 | P8: =N8-O8 -> 3000
A9: ORD108 | B9: Bilal Shah | C9: Webcam | D9: Electronics | E9: 1 | F9: 9000 | G9: 6500 | H9: 0.07 | I9: Islamabad | J9: 46243 | K9: JazzCash | L9: =E9*F9 -> 9000 | M9: =L9*H9 -> 630 | N9: =L9-M9 -> 8370 | O9: =E9*G9 -> 6500 | P9: =N9-O9 -> 1870
A10: ORD109 | B10: Zain Abbas | C10: SSD 512GB | D10: Storage | E10: 2 | F10: 14000 | G10: 11000 | H10: 0.05 | I10: Karachi | J10: 46274 | K10: Card | L10: =E10*F10 -> 28000 | M10: =L10*H10 -> 1400 | N10: =L10-M10 -> 26600 | O10: =E10*G10 -> 22000 | P10: =N10-O10 -> 4600
A11: ORD110 | B11: Maryam Khan | C11: Power Bank | D11: Accessories | E11: 4 | F11: 5000 | G11: 3500 | H11: 0.1 | I11: Lahore | J11: 46304 | K11: Cash | L11: =E11*F11 -> 20000 | M11: =L11*H11 -> 2000 | N11: =L11-M11 -> 18000 | O11: =E11*G11 -> 14000 | P11: =N11-O11 -> 4000
A12: ORD111 | B12: Saad Ahmed | C12: Laptop | D12: Electronics | E12: 2 | F12: 120000 | G12: 100000 | H12: 0.07 | I12: Rawalpindi | J12: 46335 | K12: Card | L12: =E12*F12 -> 240000 | M12: =L12*H12 -> 16800 | N12: =L12-M12 -> 223200 | O12: =E12*G12 -> 200000 | P12: =N12-O12 -> 23200
A13: ORD112 | B13: Fatima Ali | C13: Keyboard | D13: Accessories | E13: 3 | F13: 4500 | G13: 3000 | H13: 0.05 | I13: Islamabad | J13: 46365 | K13: Easypaisa | L13: =E13*F13 -> 13500 | M13: =L13*H13 -> 675 | N13: =L13-M13 -> 12825 | O13: =E13*G13 -> 9000 | P13: =N13-O13 -> 3825
A14: ORD113 | B14: Hassan Raza | C14: Monitor | D14: Electronics | E14: 1 | F14: 45000 | G14: 36000 | H14: 0.1 | I14: Karachi | J14: 13/09/2026 | K14: Card | L14: =E14*F14 -> 45000 | M14: =L14*H14 -> 4500 | N14: =L14-M14 -> 40500 | O14: =E14*G14 -> 36000 | P14: =N14-O14 -> 4500
A15: ORD114 | B15: Noor Fatima | C15: SSD 512GB | D15: Storage | E15: 3 | F15: 14000 | G15: 11000 | H15: 0.08 | I15: Lahore | J15: 14/09/2026 | K15: JazzCash | L15: =E15*F15 -> 42000 | M15: =L15*H15 -> 3360 | N15: =L15-M15 -> 38640 | O15: =E15*G15 -> 33000 | P15: =N15-O15 -> 5640
A16: ORD115 | B16: Umar Khan | C16: Mouse | D16: Accessories | E16: 5 | F16: 2500 | G16: 1800 | H16: 0.05 | I16: Islamabad | J16: 15/09/2026 | K16: Cash | L16: =E16*F16 -> 12500 | M16: =L16*H16 -> 625 | N16: =L16-M16 -> 11875 | O16: =E16*G16 -> 9000 | P16: =N16-O16 -> 2875

Sheet Analysis
A1: A | B1: B
A2: Metric | B2: Value | C2: OVERALL PERFOMANCE
A3: Total Orders | B3: =COUNTA('Raw Data'!A2:A16) -> 15
A4: Total Units Sold | B4: =SUM('Raw Data'!E2:E16) -> 39
A5: Gross Sales | B5: =SUM('Raw Data'!L2:L16) -> 680000
A6: Total Discount | B6: =SUM('Raw Data'!M2:M16) -> 47540
A7: Net Sales | B7: =SUM('Raw Data'!N2:N16) -> 632460
A8: Total Cost | B8: =SUM('Raw Data'!O2:O16) -> 542800
A9: Total Profit | B9: =SUM('Raw Data'!P2:P16) -> 89660
A10: Average Order Value | B10: =AVERAGE('Raw Data'!N2:N16) -> 42164
A11: Average Profit per Order | B11: =AVERAGE('Raw Data'!P2:P16) -> 5977.3333
A13: A | B13: B | C13: C | D13: D | F13: CATEGORY ANALYSIS
A14: Category | B14: Net Sales | C14: Total Cost | D14: Profit
A15: Electronics | B15: =SUMIF('Raw Data'!D$2:D$16,A14,'Raw Data'!N$2:N$16) -> 0 | C15: =SUMIF('Raw Data'!D$2:D$16,A14,'Raw Data'!O$2:O$16) -> 0 | D15: =SUMIF('Raw Data'!D$2:D$16,A14,'Raw Data'!P$2:P$16) -> 0
A16: Accessories | B16: =SUMIF('Raw Data'!D$2:D$16,A15,'Raw Data'!N$2:N$16) -> 491820 | C16: =SUMIF('Raw Data'!D$2:D$16,A15,'Raw Data'!O$2:O$16) -> 432500 | D16: =SUMIF('Raw Data'!D$2:D$16,A15,'Raw Data'!P$2:P$16) -> 59320
A17: Storage | B17: =SUMIF('Raw Data'!D$2:D$16,A16,'Raw Data'!N$2:N$16) -> 75400 | C17: =SUMIF('Raw Data'!D$2:D$16,A16,'Raw Data'!O$2:O$16) -> 55300 | D17: =SUMIF('Raw Data'!D$2:D$16,A16,'Raw Data'!P$2:P$16) -> 20100
A19: CITY | B19: ORDERS | C19: NET SALES | D19: PROFIT | F19: CITY ANALYSIS
A20: ISLAMABAD | B20: =COUNTIF('Raw Data'!I$2:I$16,A20) -> 5 | C20: =SUMIF('Raw Data'!I$2:I$16,A20,'Raw Data'!N$2:N$16) -> 229870 | D20: =SUMIF('Raw Data'!I$2:I$16,A20,'Raw Data'!P$2:P$16) -> 33370
A21: RAWALPINDI | B21: =COUNTIF('Raw Data'!I$2:I$16,A21) -> 3 | C21: =SUMIF('Raw Data'!I$2:I$16,A21,'Raw Data'!N$2:N$16) -> 241350 | D21: =SUMIF('Raw Data'!I$2:I$16,A21,'Raw Data'!P$2:P$16) -> 27550
A22: LAHORE | B22: =COUNTIF('Raw Data'!I$2:I$16,A22) -> 4 | C22: =SUMIF('Raw Data'!I$2:I$16,A22,'Raw Data'!N$2:N$16) -> 71190 | D22: =SUMIF('Raw Data'!I$2:I$16,A22,'Raw Data'!P$2:P$16) -> 14690
A23: KARACHI | B23: =COUNTIF('Raw Data'!I$2:I$16,A23) -> 3 | C23: =SUMIF('Raw Data'!I$2:I$16,A23,'Raw Data'!N$2:N$16) -> 90050 | D23: =SUMIF('Raw Data'!I$2:I$16,A23,'Raw Data'!P$2:P$16) -> 14050
A26: PAYMENT METHODS | B26: ORDERS | C26: NET SALES | E26: PAYMENT METHOD ANALYSIS
A27: CASH | B27: =COUNTIF('Raw Data'!K$2:K$16,A27) -> 4 | C27: =SUMIF('Raw Data'!K$2:K$16,A27,'Raw Data'!N$2:N$16) -> 42625
A28: CARD | B28: =COUNTIF('Raw Data'!K$2:K$16,A28) -> 6 | C28: =SUMIF('Raw Data'!K$2:K$16,A28,'Raw Data'!N$2:N$16) -> 498500
A29: EASYPAISA | B29: =COUNTIF('Raw Data'!K$2:K$16,A29) -> 2 | C29: =SUMIF('Raw Data'!K$2:K$16,A29,'Raw Data'!N$2:N$16) -> 35775
A33: PRODUCT | B33: UNIT SOLDS | C33: NET SALES | D33: PROFIT | F33: PRODUCT PERFOMANCE
A34: LAPTOP | B34: =SUMIF('Raw Data'!C$2:C$16,A34,'Raw Data'!E$2:E$16) -> 3 | C34: =SUMIF('Raw Data'!C$2:C$16,A34,'Raw Data'!N$2:N$16) -> 337200 | D34: =SUMIF('Raw Data'!C$2:C$16,A34,'Raw Data'!P$2:P$16) -> 37200
A35: MOUSE | B35: =SUMIF('Raw Data'!C$2:C$16,A35,'Raw Data'!E$2:E$16) -> 8 | C35: =SUMIF('Raw Data'!C$2:C$16,A35,'Raw Data'!N$2:N$16) -> 18625 | D35: =SUMIF('Raw Data'!C$2:C$16,A35,'Raw Data'!P$2:P$16) -> 4225
A36: KEYBOARD | B36: =SUMIF('Raw Data'!C$2:C$16,A36,'Raw Data'!E$2:E$16) -> 5 | C36: =SUMIF('Raw Data'!C$2:C$16,A36,'Raw Data'!N$2:N$16) -> 21375 | D36: =SUMIF('Raw Data'!C$2:C$16,A36,'Raw Data'!P$2:P$16) -> 6375
A37: MONITOR | B37: =SUMIF('Raw Data'!C$2:C$16,A37,'Raw Data'!E$2:E$16) -> 3 | C37: =SUMIF('Raw Data'!C$2:C$16,A37,'Raw Data'!N$2:N$16) -> 123300 | D37: =SUMIF('Raw Data'!C$2:C$16,A37,'Raw Data'!P$2:P$16) -> 15300
A38: HEADPHONES | B38: =SUMIF('Raw Data'!C$2:C$16,A38,'Raw Data'!E$2:E$16) -> 3 | C38: =SUMIF('Raw Data'!C$2:C$16,A38,'Raw Data'!N$2:N$16) -> 22950 | D38: =SUMIF('Raw Data'!C$2:C$16,A38,'Raw Data'!P$2:P$16) -> 4950
A39: USB CABLE | B39: =SUMIF('Raw Data'!C$2:C$16,A39,'Raw Data'!E$2:E$16) -> 5 | C39: =SUMIF('Raw Data'!C$2:C$16,A39,'Raw Data'!N$2:N$16) -> 6000 | D39: =SUMIF('Raw Data'!C$2:C$16,A39,'Raw Data'!P$2:P$16) -> 2500
A40: LAPTOP STANDS | B40: =SUMIF('Raw Data'!C$2:C$16,A40,'Raw Data'!E$2:E$16) -> 0 | C40: =SUMIF('Raw Data'!C$2:C$16,A40,'Raw Data'!N$2:N$16) -> 0 | D40: =SUMIF('Raw Data'!C$2:C$16,A40,'Raw Data'!P$2:P$16) -> 0
A41: WEBCAM | B41: =SUMIF('Raw Data'!C$2:C$16,A41,'Raw Data'!E$2:E$16) -> 1 | C41: =SUMIF('Raw Data'!C$2:C$16,A41,'Raw Data'!N$2:N$16) -> 8370 | D41: =SUMIF('Raw Data'!C$2:C$16,A41,'Raw Data'!P$2:P$16) -> 1870
A42: SSD 512GB | B42: =SUMIF('Raw Data'!C$2:C$16,A42,'Raw Data'!E$2:E$16) -> 5 | C42: =SUMIF('Raw Data'!C$2:C$16,A42,'Raw Data'!N$2:N$16) -> 65240 | D42: =SUMIF('Raw Data'!C$2:C$16,A42,'Raw Data'!P$2:P$16) -> 10240
A43: POWER BANK | B43: =SUMIF('Raw Data'!C$2:C$16,A43,'Raw Data'!E$2:E$16) -> 4 | C43: =SUMIF('Raw Data'!C$2:C$16,A43,'Raw Data'!N$2:N$16) -> 18000 | D43: =SUMIF('Raw Data'!C$2:C$16,A43,'Raw Data'!P$2:P$16) -> 4000

Sheet Product Report
A1: PRODUCT | B1: UNITS SOLDS | C1: NET SALES | D1: PROFIT | E1: PROFIT MARGIN%
A2: LAPTOP | B2: =SUMIF('Raw Data'!C$2:C$16,A2,'Raw Data'!E$2:E$16) -> 3 | C2: =SUMIF('Raw Data'!C$2:C$16,A2,'Raw Data'!N$2:N$16) -> 337200 | D2: =SUMIF('Raw Data'!C$2:C$16,A2,'Raw Data'!P$2:P$16) -> 37200 | E2: =D2/C2 -> 0.11032028
A3: MOUSE | B3: =SUMIF('Raw Data'!C$2:C$16,A3,'Raw Data'!E$2:E$16) -> 8 | C3: =SUMIF('Raw Data'!C$2:C$16,A3,'Raw Data'!N$2:N$16) -> 18625 | D3: =SUMIF('Raw Data'!C$2:C$16,A3,'Raw Data'!P$2:P$16) -> 4225 | E3: =D3/C3 -> 0.22684564
A4: KEYBOARD | B4: =SUMIF('Raw Data'!C$2:C$16,A4,'Raw Data'!E$2:E$16) -> 5 | C4: =SUMIF('Raw Data'!C$2:C$16,A4,'Raw Data'!N$2:N$16) -> 21375 | D4: =SUMIF('Raw Data'!C$2:C$16,A4,'Raw Data'!P$2:P$16) -> 6375 | E4: =D4/C4 -> 0.29824561
A5: MONITOR | B5: =SUMIF('Raw Data'!C$2:C$16,A5,'Raw Data'!E$2:E$16) -> 3 | C5: =SUMIF('Raw Data'!C$2:C$16,A5,'Raw Data'!N$2:N$16) -> 123300 | D5: =SUMIF('Raw Data'!C$2:C$16,A5,'Raw Data'!P$2:P$16) -> 15300 | E5: =D5/C5 -> 0.12408759
A6: HEADPHONES | B6: =SUMIF('Raw Data'!C$2:C$16,A6,'Raw Data'!E$2:E$16) -> 3 | C6: =SUMIF('Raw Data'!C$2:C$16,A6,'Raw Data'!N$2:N$16) -> 22950 | D6: =SUMIF('Raw Data'!C$2:C$16,A6,'Raw Data'!P$2:P$16) -> 4950 | E6: =D6/C6 -> 0.21568627
A7: USB CABLE | B7: =SUMIF('Raw Data'!C$2:C$16,A7,'Raw Data'!E$2:E$16) -> 5 | C7: =SUMIF('Raw Data'!C$2:C$16,A7,'Raw Data'!N$2:N$16) -> 6000 | D7: =SUMIF('Raw Data'!C$2:C$16,A7,'Raw Data'!P$2:P$16) -> 2500 | E7: =D7/C7 -> 0.41666667
A8: LAPTOP STANDS | B8: =SUMIF('Raw Data'!C$2:C$16,A8,'Raw Data'!E$2:E$16) -> 0 | C8: =SUMIF('Raw Data'!C$2:C$16,A8,'Raw Data'!N$2:N$16) -> 0 | D8: =SUMIF('Raw Data'!C$2:C$16,A8,'Raw Data'!P$2:P$16) -> 0 | E8: =D8/C8 -> #DIV/0!
A9: WEBCAM | B9: =SUMIF('Raw Data'!C$2:C$16,A9,'Raw Data'!E$2:E$16) -> 1 | C9: =SUMIF('Raw Data'!C$2:C$16,A9,'Raw Data'!N$2:N$16) -> 8370 | D9: =SUMIF('Raw Data'!C$2:C$16,A9,'Raw Data'!P$2:P$16) -> 1870 | E9: =D9/C9 -> 0.22341697
A10: SSD 512GB | B10: =SUMIF('Raw Data'!C$2:C$16,A10,'Raw Data'!E$2:E$16) -> 5 | C10: =SUMIF('Raw Data'!C$2:C$16,A10,'Raw Data'!N$2:N$16) -> 65240 | D10: =SUMIF('Raw Data'!C$2:C$16,A10,'Raw Data'!P$2:P$16) -> 10240 | E10: =D10/C10 -> 0.15695892
A11: POWER BANK | B11: =SUMIF('Raw Data'!C$2:C$16,A11,'Raw Data'!E$2:E$16) -> 4 | C11: =SUMIF('Raw Data'!C$2:C$16,A11,'Raw Data'!N$2:N$16) -> 18000 | D11: =SUMIF('Raw Data'!C$2:C$16,A11,'Raw Data'!P$2:P$16) -> 4000 | E11: =D11/C11 -> 0.22222222
